odoo/addons/ladirecta/__init__.py
odoo/addons/ladirecta/__manifest__.py
odoo/addons/ladirecta/models/__init__.py
odoo/addons/ladirecta/models/contract.py
odoo/addons/ladirecta/models/correos_shipment_code.py
odoo/addons/ladirecta/models/product_template.py
odoo/addons/ladirecta/models/res_company.py
odoo/addons/ladirecta/models/res_partner.py
odoo/addons/ladirecta/reports/shipment_tag.xml
odoo/addons/ladirecta/security/ir.model.access.csv
odoo/addons/ladirecta/services/__init__.py
odoo/addons/ladirecta/services/res_partner_service.py
odoo/addons/ladirecta/views/contract.xml
odoo/addons/ladirecta/views/correos_shipment_code.xml
odoo/addons/ladirecta/views/product_template.xml
odoo/addons/ladirecta/views/res_company.xml
odoo/addons/ladirecta/views/res_partner.xml
odoo/addons/ladirecta/wizards/__init__.py
odoo/addons/ladirecta/wizards/print_shipment_tags/__init__.py
odoo/addons/ladirecta/wizards/print_shipment_tags/print_shipment_tags.py
odoo/addons/ladirecta/wizards/print_shipment_tags/print_shipment_tags.xml
odoo_addon_ladirecta-16.0.1.1.0.dist-info/METADATA
odoo_addon_ladirecta-16.0.1.1.0.dist-info/WHEEL
odoo_addon_ladirecta-16.0.1.1.0.dist-info/top_level.txt
odoo_addon_ladirecta-16.0.1.1.0.dist-info/RECORD
